{
  "version": "7",
  "dialect": "postgresql",
  "entries": [
    {
      "idx": 0,
      "version": "7",
      "when": 1775409055578,
      "tag": "0000_dazzling_ezekiel_stane",
      "breakpoints": true
    },
    {
      "idx": 1,
      "version": "7",
      "when": 1775410267552,
      "tag": "0001_parallel_onslaught",
      "breakpoints": true
    },
    {
      "idx": 2,
      "version": "7",
      "when": 1775428828069,
      "tag": "0002_fixed_runaways",
      "breakpoints": true
    },
    {
      "idx": 3,
      "version": "7",
      "when": 1775623424633,
      "tag": "0003_serious_wonder_man",
      "breakpoints": true
    },
    {
      "idx": 4,
      "version": "7",
      "when": 1776023740099,
      "tag": "0004_silent_reaper",
      "breakpoints": true
    },
    {
      "idx": 5,
      "version": "7",
      "when": 1776025164352,
      "tag": "0005_breezy_random",
      "breakpoints": true
    },
    {
      "idx": 6,
      "version": "7",
      "when": 1776029649746,
      "tag": "0006_awesome_lockjaw",
      "breakpoints": true
    },
    {
      "idx": 7,
      "version": "7",
      "when": 1776049076889,
      "tag": "0007_melted_silhouette",
      "breakpoints": true
    },
    {
      "idx": 8,
      "version": "7",
      "when": 1776190434000,
      "tag": "0008_add_oauth_scopes_and_account_email",
      "breakpoints": true
    },
    {
      "idx": 9,
      "version": "7",
      "when": 1776213073000,
      "tag": "0009_add_app_settings",
      "breakpoints": true
    },
    {
      "idx": 10,
      "version": "7",
      "when": 1776349547000,
      "tag": "0010_add_ai_cache",
      "breakpoints": true
    },
    {
      "idx": 11,
      "version": "7",
      "when": 1776468248147,
      "tag": "0011_dashing_redwing",
      "breakpoints": true
    },
    {
      "idx": 12,
      "version": "7",
      "when": 1776545993447,
      "tag": "0012_multi_user_foundation",
      "breakpoints": true
    },
    {
      "idx": 13,
      "version": "7",
      "when": 1777007700000,
      "tag": "0013_work_orders_drift_repair",
      "breakpoints": true
    },
    {
      "idx": 14,
      "version": "7",
      "when": 1777180800000,
      "tag": "0014_work_order_statuses_user_scoping",
      "breakpoints": true
    },
    {
      "idx": 15,
      "version": "7",
      "when": 1777267200000,
      "tag": "0015_add_password_changed_at",
      "breakpoints": true
    },
    {
      "idx": 16,
      "version": "7",
      "when": 1777353600000,
      "tag": "0016_password_reset_tokens",
      "breakpoints": true
    },
    {
      "idx": 17,
      "version": "7",
      "when": 1777440000000,
      "tag": "0017_users_email_verified_at",
      "breakpoints": true
    },
    {
      "idx": 18,
      "version": "7",
      "when": 1778268258461,
      "tag": "0018_add_agent_events",
      "breakpoints": true
    }
  ]
}